yamkix/__init__.py
yamkix/__main__.py
yamkix/__version__.py
yamkix/_cli.py
yamkix/args.py
yamkix/comments.py
yamkix/config.py
yamkix/errors.py
yamkix/helpers.py
yamkix/yamkix.py
yamkix/yaml_writer.py
yamkix-0.14.0.dist-info/METADATA
yamkix-0.14.0.dist-info/WHEEL
yamkix-0.14.0.dist-info/entry_points.txt
yamkix-0.14.0.dist-info/licenses/LICENSE
yamkix-0.14.0.dist-info/RECORD
