Metadata-Version: 2.4
Name: yamkix
Version: 0.14.0
Summary: An opinionated yaml formatter based on ruamel.yaml
Project-URL: Repository, https://github.com/looztra/yamkix
Author-email: Christophe Furmaniak <christophe.furmaniak@gmail.com>
License-Expression: Apache-2.0
License-File: LICENSE
Classifier: Programming Language :: Python :: 3
Classifier: Programming Language :: Python :: 3.10
Classifier: Programming Language :: Python :: 3.11
Classifier: Programming Language :: Python :: 3.12
Classifier: Topic :: Utilities
Requires-Python: >=3.10
Requires-Dist: ruamel-yaml>0.17.27
Requires-Dist: typer>=0.16.0
